afl_ai_utils/__init__.py
afl_ai_utils/bigquery_utils.py
afl_ai_utils/consts.py
afl_ai_utils/drive_utils.py
afl_ai_utils/email_utils.py
afl_ai_utils/logging_utils.py
afl_ai_utils/microsoft_utils.py
afl_ai_utils/ms_api.py
afl_ai_utils/office365_utils.py
afl_ai_utils/outlook_utils.py
afl_ai_utils/secrets_utils.py
afl_ai_utils/selenium_utils.py
afl_ai_utils/sftp_utils.py
afl_ai_utils/slack_utils.py
afl_ai_utils/text_utils.py
afl_ai_utils-0.6.8.dist-info/LICENSE
afl_ai_utils-0.6.8.dist-info/METADATA
afl_ai_utils-0.6.8.dist-info/WHEEL
afl_ai_utils-0.6.8.dist-info/top_level.txt
afl_ai_utils-0.6.8.dist-info/RECORD
