Metadata-Version: 2.1
Name: afl-ai-utils
Version: 0.6.8
Summary: A sample test package
Home-page: https://github.com/gituser/test-tackage
Author: Abhay Kumar
Author-email: abhay.kumar@arvindbrands.co.in
License: MIT
Platform: UNKNOWN
Requires-Python: >=3.8
License-File: LICENSE
Requires-Dist: google-cloud-secret-manager
Requires-Dist: requests
Requires-Dist: google-cloud-bigquery
Requires-Dist: pandas
Requires-Dist: db-dtypes
Requires-Dist: fake-headers
Requires-Dist: html5lib
Requires-Dist: webdriver-manager
